[
  {
    "kind": "Listing",
    "data": {
      "after": null,
      "dist": 1,
      "modhash": "i5lelxgi4mb581ed719e3f8437e4d444c5a281a96ca50afe7c",
      "geo_filter": "",
      "children": [
        {
          "kind": "t3",
          "data": {
            "approved_at_utc": null,
            "subreddit": "chess",
            "selftext": "I played Atomic and Crazyhouse for the first time this week, and needless to say it uh.. hasn't gone great",
            "user_reports": [],
            "saved": false,
            "mod_reason_title": null,
            "gilded": 0,
            "clicked": false,
            "title": "Sure you've been on tilt, but have you ever played SO badly that Lichess gave you a Fair Play violation warning",
            "link_flair_richtext": [
              {
                "e": "text",
                "t": "Chess Question"
              }
            ],
            "subreddit_name_prefixed": "r/chess",
            "hidden": false,
            "pwls": 6,
            "link_flair_css_class": "",
            "downs": 0,
            "thumbnail_height": 83,
            "top_awarded_type": null,
            "hide_score": false,
            "name": "t3_1u3bfp0",
            "quarantine": false,
            "link_flair_text_color": "dark",
            "upvote_ratio": 0.99,
            "author_flair_background_color": null,
            "ups": 2378,
            "total_awards_received": 0,
            "media_embed": {

            },
            "thumbnail_width": 140,
            "author_flair_template_id": null,
            "is_original_content": false,
            "author_fullname": "t2_h7iu83h9",
            "secure_media": null,
            "is_reddit_media_domain": true,
            "is_meta": false,
            "category": null,
            "secure_media_embed": {

            },
            "link_flair_text": "Chess Question",
            "can_mod_post": false,
            "score": 2378,
            "approved_by": null,
            "is_created_from_ads_ui": false,
            "author_premium": false,
            "thumbnail": "https://preview.redd.it/mpoqftfivp6h1.png?width=140&height=83&auto=webp&s=ce035a8822ff877c120c67ee5f5dd80a0f8c9f7e",
            "edited": false,
            "author_flair_css_class": null,
            "author_flair_richtext": [],
            "gildings": {

            },
            "post_hint": "image",
            "content_categories": null,
            "is_self": false,
            "subreddit_type": "public",
            "created": 1781211865,
            "link_flair_type": "richtext",
            "wls": 6,
            "removed_by_category": null,
            "banned_by": null,
            "author_flair_type": "text",
            "domain": "i.redd.it",
            "allow_live_comments": false,
            "selftext_html": "\u003C!-- SC_OFF --\u003E\u003Cdiv class=\"md\"\u003E\u003Cp\u003EI played Atomic and Crazyhouse for the first time this week, and needless to say it uh.. hasn&#39;t gone great\u003C/p\u003E\n\u003C/div\u003E\u003C!-- SC_ON --\u003E",
            "likes": null,
            "suggested_sort": null,
            "banned_at_utc": null,
            "url_overridden_by_dest": "https://i.redd.it/mpoqftfivp6h1.png",
            "view_count": null,
            "archived": false,
            "no_follow": false,
            "is_crosspostable": true,
            "pinned": false,
            "over_18": false,
            "preview": {
              "images": [
                {
                  "source": {
                    "url": "https://preview.redd.it/mpoqftfivp6h1.png?auto=webp&s=8a42941c7e9d53cb06b4f5cc7c7acabea14d948c",
                    "width": 1294,
                    "height": 768
                  },
                  "resolutions": [
                    {
                      "url": "https://preview.redd.it/mpoqftfivp6h1.png?width=108&crop=smart&auto=webp&s=c3c0184b76fc230bf802a1ae9092e868bd371366",
                      "width": 108,
                      "height": 64
                    },
                    {
                      "url": "https://preview.redd.it/mpoqftfivp6h1.png?width=216&crop=smart&auto=webp&s=c4c42badf9af357765a41e529afdb074702727f5",
                      "width": 216,
                      "height": 128
                    },
                    {
                      "url": "https://preview.redd.it/mpoqftfivp6h1.png?width=320&crop=smart&auto=webp&s=a2f9470fb46f25b666031d1c6da5fa93e83e8f46",
                      "width": 320,
                      "height": 189
                    },
                    {
                      "url": "https://preview.redd.it/mpoqftfivp6h1.png?width=640&crop=smart&auto=webp&s=8564af3f593a2ecf9ddea2b8c6be604a5a82428e",
                      "width": 640,
                      "height": 379
                    },
                    {
                      "url": "https://preview.redd.it/mpoqftfivp6h1.png?width=960&crop=smart&auto=webp&s=53659c7910c1d7572cafc92dc5d305b33355ec4c",
                      "width": 960,
                      "height": 569
                    },
                    {
                      "url": "https://preview.redd.it/mpoqftfivp6h1.png?width=1080&crop=smart&auto=webp&s=3354651358eec1e6916da4ba9b306bcf93fabcf5",
                      "width": 1080,
                      "height": 640
                    }
                  ],
                  "variants": {

                  },
                  "id": "mpoqftfivp6h1"
                }
              ],
              "enabled": true
            },
            "all_awardings": [],
            "awarders": [],
            "media_only": false,
            "link_flair_template_id": "fbe61954-ae9c-11ea-b243-0ef410387f1d",
            "can_gild": false,
            "spoiler": false,
            "locked": false,
            "author_flair_text": null,
            "treatment_tags": [],
            "visited": false,
            "removed_by": null,
            "mod_note": null,
            "distinguished": null,
            "subreddit_id": "t5_2qhr7",
            "author_is_blocked": false,
            "mod_reason_by": null,
            "num_reports": null,
            "removal_reason": null,
            "link_flair_background_color": "#bbbdbf",
            "id": "1u3bfp0",
            "is_robot_indexable": true,
            "num_duplicates": 0,
            "report_reasons": null,
            "author": "Kokowolo",
            "discussion_type": null,
            "num_comments": 63,
            "send_replies": true,
            "media": null,
            "contest_mode": false,
            "author_patreon_flair": false,
            "author_flair_text_color": null,
            "permalink": "/r/chess/comments/1u3bfp0/sure_youve_been_on_tilt_but_have_you_ever_played/",
            "stickied": false,
            "url": "https://i.redd.it/mpoqftfivp6h1.png",
            "subreddit_subscribers": 1821544,
            "created_utc": 1781211865,
            "num_crossposts": 0,
            "mod_reports": [],
            "is_video": false
          }
        }
      ],
      "before": null
    }
  },
  {
    "kind": "Listing",
    "data": {
      "after": null,
      "dist": null,
      "modhash": "i5lelxgi4mb581ed719e3f8437e4d444c5a281a96ca50afe7c",
      "geo_filter": "",
      "children": [
        {
          "kind": "t1",
          "data": {
            "subreddit_id": "t5_2qhr7",
            "approved_at_utc": null,
            "author_is_blocked": false,
            "comment_type": null,
            "awarders": [],
            "mod_reason_by": null,
            "banned_by": null,
            "author_flair_type": "text",
            "total_awards_received": 0,
            "subreddit": "chess",
            "author_flair_template_id": null,
            "likes": null,
            "replies": "",
            "user_reports": [],
            "saved": false,
            "id": "or3zi11",
            "banned_at_utc": null,
            "mod_reason_title": null,
            "gilded": 0,
            "archived": false,
            "collapsed_reason_code": null,
            "no_follow": false,
            "author": "sbsw66",
            "can_mod_post": false,
            "created_utc": 1781211972,
            "send_replies": true,
            "parent_id": "t3_1u3bfp0",
            "score": 803,
            "author_fullname": "t2_85h5zov6",
            "approved_by": null,
            "mod_note": null,
            "all_awardings": [],
            "collapsed": false,
            "body": "this is cracking me up. talking about rubbing salt in the wound lol",
            "edited": false,
            "top_awarded_type": null,
            "author_flair_css_class": null,
            "name": "t1_or3zi11",
            "is_submitter": false,
            "downs": 0,
            "author_flair_richtext": [],
            "author_patreon_flair": false,
            "body_html": "\u003Cdiv class=\"md\"\u003E\u003Cp\u003Ethis is cracking me up. talking about rubbing salt in the wound lol\u003C/p\u003E\n\u003C/div\u003E",
            "removal_reason": null,
            "collapsed_reason": null,
            "distinguished": null,
            "associated_award": null,
            "stickied": false,
            "author_premium": false,
            "can_gild": false,
            "gildings": {

            },
            "unrepliable_reason": null,
            "author_flair_text_color": null,
            "score_hidden": false,
            "permalink": "/r/chess/comments/1u3bfp0/sure_youve_been_on_tilt_but_have_you_ever_played/or3zi11/",
            "subreddit_type": "public",
            "locked": false,
            "report_reasons": null,
            "created": 1781211972,
            "author_flair_text": null,
            "treatment_tags": [],
            "link_id": "t3_1u3bfp0",
            "subreddit_name_prefixed": "r/chess",
            "controversiality": 0,
            "depth": 0,
            "author_flair_background_color": null,
            "collapsed_because_crowd_control": null,
            "mod_reports": [],
            "num_reports": null,
            "ups": 803
          }
        },
        {
          "kind": "t1",
          "data": {
            "subreddit_id": "t5_2qhr7",
            "approved_at_utc": null,
            "author_is_blocked": false,
            "comment_type": null,
            "awarders": [],
            "mod_reason_by": null,
            "banned_by": null,
            "author_flair_type": "richtext",
            "total_awards_received": 0,
            "subreddit": "chess",
            "author_flair_template_id": "b6514812-458e-11eb-a57d-0ee418196fc7",
            "likes": null,
            "replies": {
              "kind": "Listing",
              "data": {
                "after": null,
                "dist": null,
                "modhash": "i5lelxgi4mb581ed719e3f8437e4d444c5a281a96ca50afe7c",
                "geo_filter": "",
                "children": [
                  {
                    "kind": "t1",
                    "data": {
                      "subreddit_id": "t5_2qhr7",
                      "approved_at_utc": null,
                      "author_is_blocked": false,
                      "comment_type": null,
                      "awarders": [],
                      "mod_reason_by": null,
                      "banned_by": null,
                      "author_flair_type": "text",
                      "total_awards_received": 0,
                      "subreddit": "chess",
                      "author_flair_template_id": null,
                      "likes": null,
                      "replies": "",
                      "user_reports": [],
                      "saved": false,
                      "id": "or59vhj",
                      "banned_at_utc": null,
                      "mod_reason_title": null,
                      "gilded": 0,
                      "archived": false,
                      "collapsed_reason_code": null,
                      "no_follow": false,
                      "author": "No_Fortune2897",
                      "can_mod_post": false,
                      "created_utc": 1781227275,
                      "send_replies": true,
                      "parent_id": "t1_or404a9",
                      "score": 97,
                      "author_fullname": "t2_4sdbq42z",
                      "removal_reason": null,
                      "approved_by": null,
                      "mod_note": null,
                      "all_awardings": [],
                      "body": "fr that's so fking tilting lmao, like I accidentally flagged in winning position and lichess warns me about letting me clock run out\n\n(I still much prefer lichess but their automated warnings are a little annoying sometimes haha)",
                      "edited": false,
                      "top_awarded_type": null,
                      "author_flair_css_class": null,
                      "name": "t1_or59vhj",
                      "is_submitter": false,
                      "downs": 0,
                      "author_flair_richtext": [],
                      "author_patreon_flair": false,
                      "body_html": "\u003Cdiv class=\"md\"\u003E\u003Cp\u003Efr that&#39;s so fking tilting lmao, like I accidentally flagged in winning position and lichess warns me about letting me clock run out\u003C/p\u003E\n\n\u003Cp\u003E(I still much prefer lichess but their automated warnings are a little annoying sometimes haha)\u003C/p\u003E\n\u003C/div\u003E",
                      "gildings": {

                      },
                      "collapsed_reason": null,
                      "distinguished": null,
                      "associated_award": null,
                      "stickied": false,
                      "author_premium": false,
                      "can_gild": false,
                      "link_id": "t3_1u3bfp0",
                      "unrepliable_reason": null,
                      "author_flair_text_color": null,
                      "score_hidden": false,
                      "permalink": "/r/chess/comments/1u3bfp0/sure_youve_been_on_tilt_but_have_you_ever_played/or59vhj/",
                      "subreddit_type": "public",
                      "locked": false,
                      "report_reasons": null,
                      "created": 1781227275,
                      "author_flair_text": null,
                      "treatment_tags": [],
                      "collapsed": false,
                      "subreddit_name_prefixed": "r/chess",
                      "controversiality": 0,
                      "depth": 1,
                      "author_flair_background_color": null,
                      "collapsed_because_crowd_control": null,
                      "mod_reports": [],
                      "num_reports": null,
                      "ups": 97
                    }
                  },
                  {
                    "kind": "t1",
                    "data": {
                      "subreddit_id": "t5_2qhr7",
                      "approved_at_utc": null,
                      "author_is_blocked": false,
                      "comment_type": null,
                      "awarders": [],
                      "mod_reason_by": null,
                      "banned_by": null,
                      "author_flair_type": "text",
                      "total_awards_received": 0,
                      "subreddit": "chess",
                      "author_flair_template_id": null,
                      "likes": null,
                      "replies": "",
                      "user_reports": [],
                      "saved": false,
                      "id": "or6bucp",
                      "banned_at_utc": null,
                      "mod_reason_title": null,
                      "gilded": 0,
                      "archived": false,
                      "collapsed_reason_code": null,
                      "no_follow": false,
                      "author": "Nabbottt",
                      "can_mod_post": false,
                      "created_utc": 1781242301,
                      "send_replies": true,
                      "parent_id": "t1_or404a9",
                      "score": 9,
                      "author_fullname": "t2_q60yk",
                      "removal_reason": null,
                      "approved_by": null,
                      "mod_note": null,
                      "all_awardings": [],
                      "body": "This happens to me sometimes when I'm losing but trying to figure out if there's a way out too; I don't usually actually flag on the long pause but a couple of moves later and then get told off for using my time to look for tricks. Very tilting",
                      "edited": false,
                      "top_awarded_type": null,
                      "author_flair_css_class": null,
                      "name": "t1_or6bucp",
                      "is_submitter": false,
                      "downs": 0,
                      "author_flair_richtext": [],
                      "author_patreon_flair": false,
                      "body_html": "\u003Cdiv class=\"md\"\u003E\u003Cp\u003EThis happens to me sometimes when I&#39;m losing but trying to figure out if there&#39;s a way out too; I don&#39;t usually actually flag on the long pause but a couple of moves later and then get told off for using my time to look for tricks. Very tilting\u003C/p\u003E\n\u003C/div\u003E",
                      "gildings": {

                      },
                      "collapsed_reason": null,
                      "distinguished": null,
                      "associated_award": null,
                      "stickied": false,
                      "author_premium": false,
                      "can_gild": false,
                      "link_id": "t3_1u3bfp0",
                      "unrepliable_reason": null,
                      "author_flair_text_color": null,
                      "score_hidden": false,
                      "permalink": "/r/chess/comments/1u3bfp0/sure_youve_been_on_tilt_but_have_you_ever_played/or6bucp/",
                      "subreddit_type": "public",
                      "locked": false,
                      "report_reasons": null,
                      "created": 1781242301,
                      "author_flair_text": null,
                      "treatment_tags": [],
                      "collapsed": false,
                      "subreddit_name_prefixed": "r/chess",
                      "controversiality": 0,
                      "depth": 1,
                      "author_flair_background_color": null,
                      "collapsed_because_crowd_control": null,
                      "mod_reports": [],
                      "num_reports": null,
                      "ups": 9
                    }
                  },
                  {
                    "kind": "t1",
                    "data": {
                      "subreddit_id": "t5_2qhr7",
                      "approved_at_utc": null,
                      "author_is_blocked": false,
                      "comment_type": null,
                      "awarders": [],
                      "mod_reason_by": null,
                      "banned_by": null,
                      "author_flair_type": "text",
                      "total_awards_received": 0,
                      "subreddit": "chess",
                      "author_flair_template_id": null,
                      "likes": null,
                      "replies": "",
                      "user_reports": [],
                      "saved": false,
                      "id": "or6rbcy",
                      "banned_at_utc": null,
                      "mod_reason_title": null,
                      "gilded": 0,
                      "archived": false,
                      "collapsed_reason_code": null,
                      "no_follow": false,
                      "author": "HardBart",
                      "can_mod_post": false,
                      "created_utc": 1781250001,
                      "send_replies": true,
                      "parent_id": "t1_or404a9",
                      "score": 9,
                      "author_fullname": "t2_bveolfb1",
                      "removal_reason": null,
                      "approved_by": null,
                      "mod_note": null,
                      "all_awardings": [],
                      "body": "Yeah, this  \n\n\"wait I'm *losing* here?!\"  \nStockfish: \"nae yer not\"",
                      "edited": false,
                      "top_awarded_type": null,
                      "author_flair_css_class": null,
                      "name": "t1_or6rbcy",
                      "is_submitter": false,
                      "downs": 0,
                      "author_flair_richtext": [],
                      "author_patreon_flair": false,
                      "body_html": "\u003Cdiv class=\"md\"\u003E\u003Cp\u003EYeah, this  \u003C/p\u003E\n\n\u003Cp\u003E&quot;wait I&#39;m \u003Cem\u003Elosing\u003C/em\u003E here?!&quot;\u003Cbr/\u003E\nStockfish: &quot;nae yer not&quot;\u003C/p\u003E\n\u003C/div\u003E",
                      "gildings": {

                      },
                      "collapsed_reason": null,
                      "distinguished": null,
                      "associated_award": null,
                      "stickied": false,
                      "author_premium": false,
                      "can_gild": false,
                      "link_id": "t3_1u3bfp0",
                      "unrepliable_reason": null,
                      "author_flair_text_color": null,
                      "score_hidden": false,
                      "permalink": "/r/chess/comments/1u3bfp0/sure_youve_been_on_tilt_but_have_you_ever_played/or6rbcy/",
                      "subreddit_type": "public",
                      "locked": false,
                      "report_reasons": null,
                      "created": 1781250001,
                      "author_flair_text": null,
                      "treatment_tags": [],
                      "collapsed": false,
                      "subreddit_name_prefixed": "r/chess",
                      "controversiality": 0,
                      "depth": 1,
                      "author_flair_background_color": null,
                      "collapsed_because_crowd_control": null,
                      "mod_reports": [],
                      "num_reports": null,
                      "ups": 9
                    }
                  }
                ],
                "before": null
              }
            },
            "user_reports": [],
            "saved": false,
            "id": "or404a9",
            "banned_at_utc": null,
            "mod_reason_title": null,
            "gilded": 0,
            "archived": false,
            "collapsed_reason_code": null,
            "no_follow": false,
            "author": "yubacore",
            "can_mod_post": false,
            "created_utc": 1781212146,
            "send_replies": true,
            "parent_id": "t3_1u3bfp0",
            "score": 385,
            "author_fullname": "t2_14obvr",
            "approved_by": null,
            "mod_note": null,
            "all_awardings": [],
            "collapsed": false,
            "body": "No, but I have been warned multiple times about letting my time run out in a losing position, by letting my time run out in a winning position.",
            "edited": false,
            "top_awarded_type": null,
            "author_flair_css_class": null,
            "name": "t1_or404a9",
            "is_submitter": false,
            "downs": 0,
            "author_flair_richtext": [
              {
                "e": "text",
                "t": "Sometimes remembers how the knight moves (2000 fide)"
              }
            ],
            "author_patreon_flair": false,
            "body_html": "\u003Cdiv class=\"md\"\u003E\u003Cp\u003ENo, but I have been warned multiple times about letting my time run out in a losing position, by letting my time run out in a winning position.\u003C/p\u003E\n\u003C/div\u003E",
            "removal_reason": null,
            "collapsed_reason": null,
            "distinguished": null,
            "associated_award": null,
            "stickied": false,
            "author_premium": false,
            "can_gild": false,
            "gildings": {

            },
            "unrepliable_reason": null,
            "author_flair_text_color": "dark",
            "score_hidden": false,
            "permalink": "/r/chess/comments/1u3bfp0/sure_youve_been_on_tilt_but_have_you_ever_played/or404a9/",
            "subreddit_type": "public",
            "locked": false,
            "report_reasons": null,
            "created": 1781212146,
            "author_flair_text": "Sometimes remembers how the knight moves (2000 fide)",
            "treatment_tags": [],
            "link_id": "t3_1u3bfp0",
            "subreddit_name_prefixed": "r/chess",
            "controversiality": 0,
            "depth": 0,
            "author_flair_background_color": "transparent",
            "collapsed_because_crowd_control": null,
            "mod_reports": [],
            "num_reports": null,
            "ups": 385
          }
        },
        {
          "kind": "t1",
          "data": {
            "subreddit_id": "t5_2qhr7",
            "approved_at_utc": null,
            "author_is_blocked": false,
            "comment_type": null,
            "awarders": [],
            "mod_reason_by": null,
            "banned_by": null,
            "author_flair_type": "text",
            "total_awards_received": 0,
            "subreddit": "chess",
            "author_flair_template_id": null,
            "likes": null,
            "replies": {
              "kind": "Listing",
              "data": {
                "after": null,
                "dist": null,
                "modhash": "i5lelxgi4mb581ed719e3f8437e4d444c5a281a96ca50afe7c",
                "geo_filter": "",
                "children": [
                  {
                    "kind": "t1",
                    "data": {
                      "subreddit_id": "t5_2qhr7",
                      "approved_at_utc": null,
                      "author_is_blocked": false,
                      "comment_type": null,
                      "awarders": [],
                      "mod_reason_by": null,
                      "banned_by": null,
                      "author_flair_type": "text",
                      "total_awards_received": 0,
                      "subreddit": "chess",
                      "author_flair_template_id": null,
                      "likes": null,
                      "replies": "",
                      "user_reports": [],
                      "saved": false,
                      "id": "or4zv1y",
                      "banned_at_utc": null,
                      "mod_reason_title": null,
                      "gilded": 0,
                      "archived": false,
                      "collapsed_reason_code": null,
                      "no_follow": false,
                      "author": "TastyCuttlefish",
                      "can_mod_post": false,
                      "created_utc": 1781223695,
                      "send_replies": true,
                      "parent_id": "t1_or4dgan",
                      "score": 108,
                      "author_fullname": "t2_16c7e4cv",
                      "removal_reason": null,
                      "approved_by": null,
                      "mod_note": null,
                      "all_awardings": [],
                      "body": "It’s called tax loss harvesting and it’s classy",
                      "edited": false,
                      "top_awarded_type": null,
                      "author_flair_css_class": null,
                      "name": "t1_or4zv1y",
                      "is_submitter": false,
                      "downs": 0,
                      "author_flair_richtext": [],
                      "author_patreon_flair": false,
                      "body_html": "\u003Cdiv class=\"md\"\u003E\u003Cp\u003EIt’s called tax loss harvesting and it’s classy\u003C/p\u003E\n\u003C/div\u003E",
                      "gildings": {

                      },
                      "collapsed_reason": null,
                      "distinguished": null,
                      "associated_award": null,
                      "stickied": false,
                      "author_premium": true,
                      "can_gild": false,
                      "link_id": "t3_1u3bfp0",
                      "unrepliable_reason": null,
                      "author_flair_text_color": null,
                      "score_hidden": false,
                      "permalink": "/r/chess/comments/1u3bfp0/sure_youve_been_on_tilt_but_have_you_ever_played/or4zv1y/",
                      "subreddit_type": "public",
                      "locked": false,
                      "report_reasons": null,
                      "created": 1781223695,
                      "author_flair_text": null,
                      "treatment_tags": [],
                      "collapsed": false,
                      "subreddit_name_prefixed": "r/chess",
                      "controversiality": 0,
                      "depth": 1,
                      "author_flair_background_color": null,
                      "collapsed_because_crowd_control": null,
                      "mod_reports": [],
                      "num_reports": null,
                      "ups": 108
                    }
                  },
                  {
                    "kind": "more",
                    "data": {
                      "count": 1,
                      "name": "t1_os1ge9y",
                      "id": "os1ge9y",
                      "parent_id": "t1_or4dgan",
                      "depth": 1,
                      "children": [
                        "os1ge9y"
                      ]
                    }
                  }
                ],
                "before": null
              }
            },
            "user_reports": [],
            "saved": false,
            "id": "or4dgan",
            "banned_at_utc": null,
            "mod_reason_title": null,
            "gilded": 0,
            "archived": false,
            "collapsed_reason_code": null,
            "no_follow": false,
            "author": "IVgormino",
            "can_mod_post": false,
            "created_utc": 1781216103,
            "send_replies": true,
            "parent_id": "t3_1u3bfp0",
            "score": 345,
            "author_fullname": "t2_13gr3l7",
            "approved_by": null,
            "mod_note": null,
            "all_awardings": [],
            "collapsed": false,
            "body": "This is like the guy who got a letter from fidelity asking him to review whether his trades resulting in a 60K loss were ”consistant with his investment objectives”",
            "edited": false,
            "top_awarded_type": null,
            "author_flair_css_class": null,
            "name": "t1_or4dgan",
            "is_submitter": false,
            "downs": 0,
            "author_flair_richtext": [],
            "author_patreon_flair": false,
            "body_html": "\u003Cdiv class=\"md\"\u003E\u003Cp\u003EThis is like the guy who got a letter from fidelity asking him to review whether his trades resulting in a 60K loss were ”consistant with his investment objectives”\u003C/p\u003E\n\u003C/div\u003E",
            "removal_reason": null,
            "collapsed_reason": null,
            "distinguished": null,
            "associated_award": null,
            "stickied": false,
            "author_premium": false,
            "can_gild": false,
            "gildings": {

            },
            "unrepliable_reason": null,
            "author_flair_text_color": null,
            "score_hidden": false,
            "permalink": "/r/chess/comments/1u3bfp0/sure_youve_been_on_tilt_but_have_you_ever_played/or4dgan/",
            "subreddit_type": "public",
            "locked": false,
            "report_reasons": null,
            "created": 1781216103,
            "author_flair_text": null,
            "treatment_tags": [],
            "link_id": "t3_1u3bfp0",
            "subreddit_name_prefixed": "r/chess",
            "controversiality": 0,
            "depth": 0,
            "author_flair_background_color": null,
            "collapsed_because_crowd_control": null,
            "mod_reports": [],
            "num_reports": null,
            "ups": 345
          }
        },
        {
          "kind": "t1",
          "data": {
            "subreddit_id": "t5_2qhr7",
            "approved_at_utc": null,
            "author_is_blocked": false,
            "comment_type": null,
            "awarders": [],
            "mod_reason_by": null,
            "banned_by": null,
            "author_flair_type": "richtext",
            "total_awards_received": 0,
            "subreddit": "chess",
            "author_flair_template_id": "b6514812-458e-11eb-a57d-0ee418196fc7",
            "likes": null,
            "replies": "",
            "user_reports": [],
            "saved": false,
            "id": "or3zlu7",
            "banned_at_utc": null,
            "mod_reason_title": null,
            "gilded": 0,
            "archived": false,
            "collapsed_reason_code": null,
            "no_follow": false,
            "author": "Agreeable_Sun3713",
            "can_mod_post": false,
            "created_utc": 1781212001,
            "send_replies": true,
            "parent_id": "t3_1u3bfp0",
            "score": 74,
            "author_fullname": "t2_40yjwhjdp",
            "approved_by": null,
            "mod_note": null,
            "all_awardings": [],
            "collapsed": false,
            "body": "5 times in a span 10 months!!",
            "edited": false,
            "top_awarded_type": null,
            "author_flair_css_class": null,
            "name": "t1_or3zlu7",
            "is_submitter": false,
            "downs": 0,
            "author_flair_richtext": [
              {
                "e": "text",
                "t": "Team Sagar Shah"
              }
            ],
            "author_patreon_flair": false,
            "body_html": "\u003Cdiv class=\"md\"\u003E\u003Cp\u003E5 times in a span 10 months!!\u003C/p\u003E\n\u003C/div\u003E",
            "removal_reason": null,
            "collapsed_reason": null,
            "distinguished": null,
            "associated_award": null,
            "stickied": false,
            "author_premium": false,
            "can_gild": false,
            "gildings": {

            },
            "unrepliable_reason": null,
            "author_flair_text_color": "dark",
            "score_hidden": false,
            "permalink": "/r/chess/comments/1u3bfp0/sure_youve_been_on_tilt_but_have_you_ever_played/or3zlu7/",
            "subreddit_type": "public",
            "locked": false,
            "report_reasons": null,
            "created": 1781212001,
            "author_flair_text": "Team Sagar Shah",
            "treatment_tags": [],
            "link_id": "t3_1u3bfp0",
            "subreddit_name_prefixed": "r/chess",
            "controversiality": 0,
            "depth": 0,
            "author_flair_background_color": "transparent",
            "collapsed_because_crowd_control": null,
            "mod_reports": [],
            "num_reports": null,
            "ups": 74
          }
        },
        {
          "kind": "t1",
          "data": {
            "subreddit_id": "t5_2qhr7",
            "approved_at_utc": null,
            "author_is_blocked": false,
            "comment_type": null,
            "awarders": [],
            "mod_reason_by": null,
            "banned_by": null,
            "author_flair_type": "text",
            "total_awards_received": 0,
            "subreddit": "chess",
            "author_flair_template_id": null,
            "likes": null,
            "replies": "",
            "user_reports": [],
            "saved": false,
            "id": "or46ron",
            "banned_at_utc": null,
            "mod_reason_title": null,
            "gilded": 0,
            "archived": false,
            "collapsed_reason_code": null,
            "no_follow": false,
            "author": "vernichtungX23",
            "can_mod_post": false,
            "created_utc": 1781214059,
            "send_replies": true,
            "parent_id": "t3_1u3bfp0",
            "score": 72,
            "author_fullname": "t2_16ud2zl5xn",
            "approved_by": null,
            "mod_note": null,
            "all_awardings": [],
            "collapsed": false,
            "body": "This always happened to me when I went from a slow time control to a faster one. I'm glad they're being a bit kinder about it. I got a very snotty message accusing me of sandbagging because I lost early in ultrabullet. *Ultrabullet.*",
            "edited": false,
            "top_awarded_type": null,
            "author_flair_css_class": null,
            "name": "t1_or46ron",
            "is_submitter": false,
            "downs": 0,
            "author_flair_richtext": [],
            "author_patreon_flair": false,
            "body_html": "\u003Cdiv class=\"md\"\u003E\u003Cp\u003EThis always happened to me when I went from a slow time control to a faster one. I&#39;m glad they&#39;re being a bit kinder about it. I got a very snotty message accusing me of sandbagging because I lost early in ultrabullet. \u003Cem\u003EUltrabullet.\u003C/em\u003E\u003C/p\u003E\n\u003C/div\u003E",
            "removal_reason": null,
            "collapsed_reason": null,
            "distinguished": null,
            "associated_award": null,
            "stickied": false,
            "author_premium": false,
            "can_gild": false,
            "gildings": {

            },
            "unrepliable_reason": null,
            "author_flair_text_color": null,
            "score_hidden": false,
            "permalink": "/r/chess/comments/1u3bfp0/sure_youve_been_on_tilt_but_have_you_ever_played/or46ron/",
            "subreddit_type": "public",
            "locked": false,
            "report_reasons": null,
            "created": 1781214059,
            "author_flair_text": null,
            "treatment_tags": [],
            "link_id": "t3_1u3bfp0",
            "subreddit_name_prefixed": "r/chess",
            "controversiality": 0,
            "depth": 0,
            "author_flair_background_color": null,
            "collapsed_because_crowd_control": null,
            "mod_reports": [],
            "num_reports": null,
            "ups": 72
          }
        },
        {
          "kind": "t1",
          "data": {
            "subreddit_id": "t5_2qhr7",
            "approved_at_utc": null,
            "author_is_blocked": false,
            "comment_type": null,
            "awarders": [],
            "mod_reason_by": null,
            "banned_by": null,
            "author_flair_type": "richtext",
            "total_awards_received": 0,
            "subreddit": "chess",
            "author_flair_template_id": "b6514812-458e-11eb-a57d-0ee418196fc7",
            "likes": null,
            "replies": {
              "kind": "Listing",
              "data": {
                "after": null,
                "dist": null,
                "modhash": "i5lelxgi4mb581ed719e3f8437e4d444c5a281a96ca50afe7c",
                "geo_filter": "",
                "children": [
                  {
                    "kind": "t1",
                    "data": {
                      "subreddit_id": "t5_2qhr7",
                      "approved_at_utc": null,
                      "author_is_blocked": false,
                      "comment_type": null,
                      "awarders": [],
                      "mod_reason_by": null,
                      "banned_by": null,
                      "author_flair_type": "text",
                      "total_awards_received": 0,
                      "subreddit": "chess",
                      "author_flair_template_id": null,
                      "likes": null,
                      "replies": "",
                      "user_reports": [],
                      "saved": false,
                      "id": "or4d07h",
                      "banned_at_utc": null,
                      "mod_reason_title": null,
                      "gilded": 0,
                      "archived": false,
                      "collapsed_reason_code": null,
                      "no_follow": false,
                      "author": "Kokowolo",
                      "can_mod_post": false,
                      "created_utc": 1781215963,
                      "send_replies": true,
                      "parent_id": "t1_or4axdj",
                      "score": 38,
                      "author_fullname": "t2_h7iu83h9",
                      "removal_reason": null,
                      "approved_by": null,
                      "mod_note": null,
                      "all_awardings": [],
                      "body": "\"nah bro you can't possibly be that bad\"",
                      "edited": false,
                      "top_awarded_type": null,
                      "author_flair_css_class": null,
                      "name": "t1_or4d07h",
                      "is_submitter": true,
                      "downs": 0,
                      "author_flair_richtext": [],
                      "author_patreon_flair": false,
                      "body_html": "\u003Cdiv class=\"md\"\u003E\u003Cp\u003E&quot;nah bro you can&#39;t possibly be that bad&quot;\u003C/p\u003E\n\u003C/div\u003E",
                      "gildings": {

                      },
                      "collapsed_reason": null,
                      "distinguished": null,
                      "associated_award": null,
                      "stickied": false,
                      "author_premium": false,
                      "can_gild": false,
                      "link_id": "t3_1u3bfp0",
                      "unrepliable_reason": null,
                      "author_flair_text_color": null,
                      "score_hidden": false,
                      "permalink": "/r/chess/comments/1u3bfp0/sure_youve_been_on_tilt_but_have_you_ever_played/or4d07h/",
                      "subreddit_type": "public",
                      "locked": false,
                      "report_reasons": null,
                      "created": 1781215963,
                      "author_flair_text": null,
                      "treatment_tags": [],
                      "collapsed": false,
                      "subreddit_name_prefixed": "r/chess",
                      "controversiality": 0,
                      "depth": 1,
                      "author_flair_background_color": null,
                      "collapsed_because_crowd_control": null,
                      "mod_reports": [],
                      "num_reports": null,
                      "ups": 38
                    }
                  }
                ],
                "before": null
              }
            },
            "user_reports": [],
            "saved": false,
            "id": "or4axdj",
            "banned_at_utc": null,
            "mod_reason_title": null,
            "gilded": 0,
            "archived": false,
            "collapsed_reason_code": null,
            "no_follow": false,
            "author": "Kerbart",
            "can_mod_post": false,
            "created_utc": 1781215315,
            "send_replies": true,
            "parent_id": "t3_1u3bfp0",
            "score": 71,
            "author_fullname": "t2_afp41b",
            "approved_by": null,
            "mod_note": null,
            "all_awardings": [],
            "collapsed": false,
            "body": "\"You sucked more in this session than we think is humanly possible\"",
            "edited": false,
            "top_awarded_type": null,
            "author_flair_css_class": null,
            "name": "t1_or4axdj",
            "is_submitter": false,
            "downs": 0,
            "author_flair_richtext": [
              {
                "e": "text",
                "t": " ~1450 USCF"
              }
            ],
            "author_patreon_flair": false,
            "body_html": "\u003Cdiv class=\"md\"\u003E\u003Cp\u003E&quot;You sucked more in this session than we think is humanly possible&quot;\u003C/p\u003E\n\u003C/div\u003E",
            "removal_reason": null,
            "collapsed_reason": null,
            "distinguished": null,
            "associated_award": null,
            "stickied": false,
            "author_premium": false,
            "can_gild": false,
            "gildings": {

            },
            "unrepliable_reason": null,
            "author_flair_text_color": "dark",
            "score_hidden": false,
            "permalink": "/r/chess/comments/1u3bfp0/sure_youve_been_on_tilt_but_have_you_ever_played/or4axdj/",
            "subreddit_type": "public",
            "locked": false,
            "report_reasons": null,
            "created": 1781215315,
            "author_flair_text": " ~1450 USCF",
            "treatment_tags": [],
            "link_id": "t3_1u3bfp0",
            "subreddit_name_prefixed": "r/chess",
            "controversiality": 0,
            "depth": 0,
            "author_flair_background_color": "transparent",
            "collapsed_because_crowd_control": null,
            "mod_reports": [],
            "num_reports": null,
            "ups": 71
          }
        },
        {
          "kind": "t1",
          "data": {
            "subreddit_id": "t5_2qhr7",
            "approved_at_utc": null,
            "author_is_blocked": false,
            "comment_type": null,
            "awarders": [],
            "mod_reason_by": null,
            "banned_by": null,
            "author_flair_type": "text",
            "total_awards_received": 0,
            "subreddit": "chess",
            "author_flair_template_id": null,
            "likes": null,
            "replies": "",
            "user_reports": [],
            "saved": false,
            "id": "or4ryyu",
            "banned_at_utc": null,
            "mod_reason_title": null,
            "gilded": 0,
            "archived": false,
            "collapsed_reason_code": null,
            "no_follow": false,
            "author": "2freaky3",
            "can_mod_post": false,
            "created_utc": 1781220918,
            "send_replies": true,
            "parent_id": "t3_1u3bfp0",
            "score": 44,
            "author_fullname": "t2_28c2jl4odp",
            "approved_by": null,
            "mod_note": null,
            "all_awardings": [],
            "collapsed": false,
            "body": "i would crash the FUCK out seeing this message lmao",
            "edited": false,
            "top_awarded_type": null,
            "author_flair_css_class": null,
            "name": "t1_or4ryyu",
            "is_submitter": false,
            "downs": 0,
            "author_flair_richtext": [],
            "author_patreon_flair": false,
            "body_html": "\u003Cdiv class=\"md\"\u003E\u003Cp\u003Ei would crash the FUCK out seeing this message lmao\u003C/p\u003E\n\u003C/div\u003E",
            "removal_reason": null,
            "collapsed_reason": null,
            "distinguished": null,
            "associated_award": null,
            "stickied": false,
            "author_premium": false,
            "can_gild": false,
            "gildings": {

            },
            "unrepliable_reason": null,
            "author_flair_text_color": null,
            "score_hidden": false,
            "permalink": "/r/chess/comments/1u3bfp0/sure_youve_been_on_tilt_but_have_you_ever_played/or4ryyu/",
            "subreddit_type": "public",
            "locked": false,
            "report_reasons": null,
            "created": 1781220918,
            "author_flair_text": null,
            "treatment_tags": [],
            "link_id": "t3_1u3bfp0",
            "subreddit_name_prefixed": "r/chess",
            "controversiality": 0,
            "depth": 0,
            "author_flair_background_color": null,
            "collapsed_because_crowd_control": null,
            "mod_reports": [],
            "num_reports": null,
            "ups": 44
          }
        },
        {
          "kind": "t1",
          "data": {
            "subreddit_id": "t5_2qhr7",
            "approved_at_utc": null,
            "author_is_blocked": false,
            "comment_type": null,
            "awarders": [],
            "mod_reason_by": null,
            "banned_by": null,
            "author_flair_type": "richtext",
            "total_awards_received": 0,
            "subreddit": "chess",
            "author_flair_template_id": null,
            "likes": null,
            "replies": "",
            "user_reports": [],
            "saved": false,
            "id": "or4256x",
            "banned_at_utc": null,
            "mod_reason_title": null,
            "gilded": 0,
            "archived": false,
            "collapsed_reason_code": null,
            "no_follow": false,
            "author": "SoChessGoes",
            "can_mod_post": false,
            "created_utc": 1781212718,
            "send_replies": true,
            "parent_id": "t3_1u3bfp0",
            "score": 19,
            "author_fullname": "t2_r6sj7",
            "approved_by": null,
            "mod_note": null,
            "all_awardings": [],
            "collapsed": false,
            "body": "That happened to me the other week, but it was while I was playing in a bullet tournament. And I had only lost like 2 games out of 5 or something. It was very strange. ",
            "edited": false,
            "top_awarded_type": null,
            "author_flair_css_class": null,
            "name": "t1_or4256x",
            "is_submitter": false,
            "downs": 0,
            "author_flair_richtext": [
              {
                "e": "text",
                "t": "USCF 1800"
              }
            ],
            "author_patreon_flair": false,
            "body_html": "\u003Cdiv class=\"md\"\u003E\u003Cp\u003EThat happened to me the other week, but it was while I was playing in a bullet tournament. And I had only lost like 2 games out of 5 or something. It was very strange. \u003C/p\u003E\n\u003C/div\u003E",
            "removal_reason": null,
            "collapsed_reason": null,
            "distinguished": null,
            "associated_award": null,
            "stickied": false,
            "author_premium": false,
            "can_gild": false,
            "gildings": {

            },
            "unrepliable_reason": null,
            "author_flair_text_color": "dark",
            "score_hidden": false,
            "permalink": "/r/chess/comments/1u3bfp0/sure_youve_been_on_tilt_but_have_you_ever_played/or4256x/",
            "subreddit_type": "public",
            "locked": false,
            "report_reasons": null,
            "created": 1781212718,
            "author_flair_text": "USCF 1800",
            "treatment_tags": [],
            "link_id": "t3_1u3bfp0",
            "subreddit_name_prefixed": "r/chess",
            "controversiality": 0,
            "depth": 0,
            "author_flair_background_color": "",
            "collapsed_because_crowd_control": null,
            "mod_reports": [],
            "num_reports": null,
            "ups": 19
          }
        },
        {
          "kind": "t1",
          "data": {
            "subreddit_id": "t5_2qhr7",
            "approved_at_utc": null,
            "author_is_blocked": false,
            "comment_type": null,
            "awarders": [],
            "mod_reason_by": null,
            "banned_by": null,
            "author_flair_type": "text",
            "total_awards_received": 0,
            "subreddit": "chess",
            "author_flair_template_id": null,
            "likes": null,
            "replies": {
              "kind": "Listing",
              "data": {
                "after": null,
                "dist": null,
                "modhash": "i5lelxgi4mb581ed719e3f8437e4d444c5a281a96ca50afe7c",
                "geo_filter": "",
                "children": [
                  {
                    "kind": "more",
                    "data": {
                      "count": 1,
                      "name": "t1_or6o2pu",
                      "id": "or6o2pu",
                      "parent_id": "t1_or43k2n",
                      "depth": 1,
                      "children": [
                        "or6o2pu"
                      ]
                    }
                  }
                ],
                "before": null
              }
            },
            "user_reports": [],
            "saved": false,
            "id": "or43k2n",
            "banned_at_utc": null,
            "mod_reason_title": null,
            "gilded": 0,
            "archived": false,
            "collapsed_reason_code": null,
            "no_follow": false,
            "author": "wilyodysseus89",
            "can_mod_post": false,
            "created_utc": 1781213121,
            "send_replies": true,
            "parent_id": "t3_1u3bfp0",
            "score": 13,
            "author_fullname": "t2_4mb4vn4y",
            "approved_by": null,
            "mod_note": null,
            "all_awardings": [],
            "collapsed": false,
            "body": "I tilt like 50-80 point swings in blitz somewhat regularly (maybe once or twice a month) and then terrorize the rating pool on my way back up within a week. Have *never* gotten this message before. Once during a late night tilt session I even had a game go d4 d5 2. C4 e6 3. Nc3 nf6 4. Cxd5 nxd5 5. Bg5 (premoved) qxg5 resigns. ",
            "edited": false,
            "top_awarded_type": null,
            "author_flair_css_class": null,
            "name": "t1_or43k2n",
            "is_submitter": false,
            "downs": 0,
            "author_flair_richtext": [],
            "author_patreon_flair": false,
            "body_html": "\u003Cdiv class=\"md\"\u003E\u003Cp\u003EI tilt like 50-80 point swings in blitz somewhat regularly (maybe once or twice a month) and then terrorize the rating pool on my way back up within a week. Have \u003Cem\u003Enever\u003C/em\u003E gotten this message before. Once during a late night tilt session I even had a game go d4 d5 2. C4 e6 3. Nc3 nf6 4. Cxd5 nxd5 5. Bg5 (premoved) qxg5 resigns. \u003C/p\u003E\n\u003C/div\u003E",
            "removal_reason": null,
            "collapsed_reason": null,
            "distinguished": null,
            "associated_award": null,
            "stickied": false,
            "author_premium": false,
            "can_gild": false,
            "gildings": {

            },
            "unrepliable_reason": null,
            "author_flair_text_color": null,
            "score_hidden": false,
            "permalink": "/r/chess/comments/1u3bfp0/sure_youve_been_on_tilt_but_have_you_ever_played/or43k2n/",
            "subreddit_type": "public",
            "locked": false,
            "report_reasons": null,
            "created": 1781213121,
            "author_flair_text": null,
            "treatment_tags": [],
            "link_id": "t3_1u3bfp0",
            "subreddit_name_prefixed": "r/chess",
            "controversiality": 0,
            "depth": 0,
            "author_flair_background_color": null,
            "collapsed_because_crowd_control": null,
            "mod_reports": [],
            "num_reports": null,
            "ups": 13
          }
        },
        {
          "kind": "t1",
          "data": {
            "subreddit_id": "t5_2qhr7",
            "approved_at_utc": null,
            "author_is_blocked": false,
            "comment_type": null,
            "awarders": [],
            "mod_reason_by": null,
            "banned_by": null,
            "author_flair_type": "richtext",
            "total_awards_received": 0,
            "subreddit": "chess",
            "author_flair_template_id": "b6514812-458e-11eb-a57d-0ee418196fc7",
            "likes": null,
            "replies": "",
            "user_reports": [],
            "saved": false,
            "id": "or4kp44",
            "banned_at_utc": null,
            "mod_reason_title": null,
            "gilded": 0,
            "archived": false,
            "collapsed_reason_code": null,
            "no_follow": false,
            "author": "aandres44",
            "can_mod_post": false,
            "created_utc": 1781218461,
            "send_replies": true,
            "parent_id": "t3_1u3bfp0",
            "score": 11,
            "author_fullname": "t2_3cvqw0te",
            "approved_by": null,
            "mod_note": null,
            "all_awardings": [],
            "collapsed": false,
            "body": "Lol I have. Got this one after losing a bunch of bullet games and tilting while playing nonsense openings",
            "edited": false,
            "top_awarded_type": null,
            "author_flair_css_class": null,
            "name": "t1_or4kp44",
            "is_submitter": false,
            "downs": 0,
            "author_flair_richtext": [
              {
                "e": "text",
                "t": " 1891 FIDE 2400+ Lichess"
              }
            ],
            "author_patreon_flair": false,
            "body_html": "\u003Cdiv class=\"md\"\u003E\u003Cp\u003ELol I have. Got this one after losing a bunch of bullet games and tilting while playing nonsense openings\u003C/p\u003E\n\u003C/div\u003E",
            "removal_reason": null,
            "collapsed_reason": null,
            "distinguished": null,
            "associated_award": null,
            "stickied": false,
            "author_premium": false,
            "can_gild": false,
            "gildings": {

            },
            "unrepliable_reason": null,
            "author_flair_text_color": "dark",
            "score_hidden": false,
            "permalink": "/r/chess/comments/1u3bfp0/sure_youve_been_on_tilt_but_have_you_ever_played/or4kp44/",
            "subreddit_type": "public",
            "locked": false,
            "report_reasons": null,
            "created": 1781218461,
            "author_flair_text": " 1891 FIDE 2400+ Lichess",
            "treatment_tags": [],
            "link_id": "t3_1u3bfp0",
            "subreddit_name_prefixed": "r/chess",
            "controversiality": 0,
            "depth": 0,
            "author_flair_background_color": "transparent",
            "collapsed_because_crowd_control": null,
            "mod_reports": [],
            "num_reports": null,
            "ups": 11
          }
        },
        {
          "kind": "more",
          "data": {
            "count": 49,
            "name": "t1_or47lpl",
            "id": "or47lpl",
            "parent_id": "t3_1u3bfp0",
            "depth": 0,
            "children": [
              "or47lpl",
              "or4gr9c",
              "or75ig9",
              "orf1xk6",
              "or5zdz7",
              "or6jq4z",
              "or4rkua",
              "or4t4j3",
              "or993of",
              "ory54ht",
              "or6fpdr",
              "or6rjb3",
              "or70oz0",
              "or79375",
              "or8968w",
              "or8eluw",
              "or92mu6",
              "or5cdvz",
              "or5f1ki",
              "os3fg3u",
              "or62il7",
              "or6eqvq",
              "or4htq9",
              "or4j4bv",
              "or5g45s",
              "oretvxl",
              "os4wcx0",
              "or5a38n",
              "or7zbpq",
              "or4258f",
              "or8aa44"
            ]
          }
        }
      ],
      "before": null
    }
  }
]